management/__init__.py
management/commands/__init__.py
management/commands/runhttp3.py
utils/__init__.py
utils/asgi_utils.py
utils/ssl_utils.py
django_http3-0.1.0.dist-info/METADATA
django_http3-0.1.0.dist-info/WHEEL
django_http3-0.1.0.dist-info/top_level.txt
django_http3-0.1.0.dist-info/RECORD
