Metadata-Version: 2.1
Name: django-http3
Version: 0.1.0
Summary: A Django package for automatic HTTP/3 support
Home-page: https://github.com/hemaxox/django-http3-package
Author: Ibrahim Muhaisen
Author-email: ibrahim.muhaisen.2015@gmail.com
License: UNKNOWN
Platform: UNKNOWN
Classifier: Framework :: Django
Classifier: Programming Language :: Python :: 3
Classifier: License :: OSI Approved :: MIT License
Requires-Dist: Django>=3.0
Requires-Dist: aioquic
Requires-Dist: asgiref
